basedrow/__init__.py
basedrow/client.py
basedrow-0.3.0.dist-info/LICENSE
basedrow-0.3.0.dist-info/WHEEL
basedrow-0.3.0.dist-info/METADATA
basedrow-0.3.0.dist-info/RECORD
