Metadata-Version: 2.1
Name: basedrow
Version: 0.3.0
Summary: Baserow client for Python.
Author-email: Stephan Fitzpatrick <knowsuchagency@gmail.com>
Classifier: License :: OSI Approved :: MIT License
Requires-Dist: httpx
Requires-Dist: wmill ; extra == "windmill"
Provides-Extra: windmill
